terracomp_server/__init__.py
terracomp_server/_project.py
terracomp_server/_runs.py
terracomp_server/_server.py
terracomp_server/_state.py
terracomp_server/py.typed
terracomp_server/tfcloudapi/__init__.py
terracomp_server/tfcloudapi/_models.py
terracomp_server/tfcloudapi/_service.py
terracomp_server-0.0.8.dist-info/LICENSE
terracomp_server-0.0.8.dist-info/METADATA
terracomp_server-0.0.8.dist-info/WHEEL
terracomp_server-0.0.8.dist-info/RECORD
