Metadata-Version: 2.1
Name: terracomp-server
Version: 0.0.8
Summary: 
License: MIT
Author: Niklas Rosenstein
Author-email: rosensteinniklas@gmail.com
Requires-Python: >=3.10,<4.0
Classifier: License :: OSI Approved :: MIT License
Classifier: Programming Language :: Python :: 3
Classifier: Programming Language :: Python :: 3.10
Classifier: Programming Language :: Python :: 3.11
Requires-Dist: fastapi (>=0.95.0,<0.96.0)
Requires-Dist: terracomp-api (>=0.0.8,<0.0.9)
Requires-Dist: uvicorn (>=0.21.1,<0.22.0)
